odoo/addons/mail_activity_partner/README.rst
odoo/addons/mail_activity_partner/__init__.py
odoo/addons/mail_activity_partner/__manifest__.py
odoo/addons/mail_activity_partner/i18n/es.po
odoo/addons/mail_activity_partner/i18n/it.po
odoo/addons/mail_activity_partner/i18n/mail_activity_partner.pot
odoo/addons/mail_activity_partner/models/__init__.py
odoo/addons/mail_activity_partner/models/mail_activity.py
odoo/addons/mail_activity_partner/readme/CONTRIBUTORS.rst
odoo/addons/mail_activity_partner/readme/DESCRIPTION.rst
odoo/addons/mail_activity_partner/readme/USAGE.rst
odoo/addons/mail_activity_partner/static/description/icon.png
odoo/addons/mail_activity_partner/static/description/index.html
odoo/addons/mail_activity_partner/tests/__init__.py
odoo/addons/mail_activity_partner/tests/test_mail_activity_partner.py
odoo/addons/mail_activity_partner/views/mail_activity_views.xml
odoo14_addon_mail_activity_partner-14.0.1.0.1.dev8.dist-info/METADATA
odoo14_addon_mail_activity_partner-14.0.1.0.1.dev8.dist-info/WHEEL
odoo14_addon_mail_activity_partner-14.0.1.0.1.dev8.dist-info/top_level.txt
odoo14_addon_mail_activity_partner-14.0.1.0.1.dev8.dist-info/RECORD
